Metadata-Version: 2.1
Name: CuraPackageDeployer
Version: 1.0.0
Summary: Automatically build, deploy and distribute Ultimaker Cura Toolbox packages
Home-page: https://github.com/ChrisTerBeke/CuraPackageDeployer
Author: Chris ter Beke
Author-email: c.terbeke@ultimaker.com
License: AGPL-3.0
Platform: UNKNOWN
Classifier: Programming Language :: Python :: 3
Classifier: Operating System :: OS Independent
